{
  "users": [
    {
      "name": "Enrique Ankunding",
      "id": 3
    },
    {
      "name": "Regina Kuvalis",
      "id": 4
    },
    {
      "name": "Salvatore Barrows",
      "id": 5
    }
  ],
  "albums": [
    {
      "userId": 3,
      "title": "Sleek Plastic Cheese",
      "id": 1
    },
    {
      "userId": 4,
      "title": "Incredible Metal Bike",
      "id": 2
    },
    {
      "userId": 3,
      "title": "Luxurious Concrete Chips",
      "id": 3
    },
    {
      "userId": 4,
      "title": "Modern Wooden Table",
      "id": 4
    }
  ],
  "photos": [
    {
      "albumId": 1,
      "url": "https://loremflickr.com/100/100/abstract?lock=14976",
      "id": 1
    },
    {
      "albumId": 1,
      "url": "https://loremflickr.com/100/100/abstract?lock=66693",
      "id": 2
    },
    {
      "albumId": 2,
      "url": "https://loremflickr.com/100/100/abstract?lock=18858",
      "id": 3
    },
    {
      "albumId": 2,
      "url": "https://loremflickr.com/100/100/abstract?lock=13318",
      "id": 4
    },
    {
      "albumId": 2,
      "url": "https://loremflickr.com/100/100/abstract?lock=61889",
      "id": 5
    },
    {
      "albumId": 1,
      "url": "https://loremflickr.com/100/100/abstract?lock=78854",
      "id": 8
    },
    {
      "albumId": 3,
      "url": "https://loremflickr.com/100/100/abstract?lock=50599",
      "id": 9
    },
    {
      "albumId": 3,
      "url": "https://loremflickr.com/100/100/abstract?lock=80118",
      "id": 10
    },
    {
      "albumId": 3,
      "url": "https://loremflickr.com/100/100/abstract?lock=94392",
      "id": 11
    },
    {
      "albumId": 3,
      "url": "https://loremflickr.com/100/100/abstract?lock=47031",
      "id": 12
    },
    {
      "albumId": 3,
      "url": "https://loremflickr.com/100/100/abstract?lock=55046",
      "id": 13
    },
    {
      "albumId": 1,
      "url": "https://loremflickr.com/100/100/abstract?lock=53677",
      "id": 15
    },
    {
      "albumId": 1,
      "url": "https://loremflickr.com/100/100/abstract?lock=67785",
      "id": 16
    },
    {
      "albumId": 1,
      "url": "https://loremflickr.com/100/100/abstract?lock=75931",
      "id": 17
    },
    {
      "albumId": 2,
      "url": "https://loremflickr.com/100/100/abstract?lock=9883",
      "id": 18
    },
    {
      "albumId": 4,
      "url": "https://loremflickr.com/100/100/abstract?lock=76145",
      "id": 19
    },
    {
      "albumId": 4,
      "url": "https://loremflickr.com/100/100/abstract?lock=32502",
      "id": 20
    },
    {
      "albumId": 4,
      "url": "https://loremflickr.com/100/100/abstract?lock=59170",
      "id": 21
    },
    {
      "albumId": 4,
      "url": "https://loremflickr.com/100/100/abstract?lock=19392",
      "id": 22
    }
  ]
}